lomond/__init__.py
lomond/_version.py
lomond/compression.py
lomond/constants.py
lomond/errors.py
lomond/events.py
lomond/extension.py
lomond/frame.py
lomond/frame_parser.py
lomond/mask.py
lomond/message.py
lomond/opcode.py
lomond/parser.py
lomond/persist.py
lomond/proxy.py
lomond/response.py
lomond/selectors.py
lomond/session.py
lomond/status.py
lomond/stream.py
lomond/utf8validator.py
lomond/websocket.py
lomonds/__init__.py
lomonds/_version.py
lomonds/compression.py
lomonds/constants.py
lomonds/errors.py
lomonds/events.py
lomonds/extension.py
lomonds/frame.py
lomonds/frame_parser.py
lomonds/mask.py
lomonds/message.py
lomonds/opcode.py
lomonds/parser.py
lomonds/persist.py
lomonds/proxy.py
lomonds/response.py
lomonds/selectors.py
lomonds/session.py
lomonds/status.py
lomonds/stream.py
lomonds/utf8validator.py
lomonds/websocket.py
lomonds-0.0.2.dist-info/LICENSE.md
lomonds-0.0.2.dist-info/METADATA
lomonds-0.0.2.dist-info/WHEEL
lomonds-0.0.2.dist-info/top_level.txt
lomonds-0.0.2.dist-info/zip-safe
lomonds-0.0.2.dist-info/RECORD
