Metadata-Version: 2.1
Name: lomonds
Version: 0.0.2
Summary: Websocket Client Library
Home-page: https://github.com/iessen/dataplicity-lomond
Author: iessen
Author-email: essen.wang.sh@gmail.com
License: UNKNOWN
Platform: any
Classifier: Development Status :: 5 - Production/Stable
Classifier: Intended Audience :: Developers
Classifier: Programming Language :: Python
Classifier: License :: OSI Approved :: BSD License
Classifier: Programming Language :: Python :: 2.7
Classifier: Programming Language :: Python :: 3.3
Classifier: Programming Language :: Python :: 3.4
Classifier: Programming Language :: Python :: 3.5
Classifier: Programming Language :: Python :: 3.6
Classifier: Topic :: Internet
Requires-Dist: six (>=1.10.0)
